wikidatatool/__init__.py
wikidatatool/cli.py
wikidatatool/common.py
wikidatatool/wikidatatool.py
wikidatatool-0.0.4.dist-info/AUTHORS.rst
wikidatatool-0.0.4.dist-info/LICENSE
wikidatatool-0.0.4.dist-info/METADATA
wikidatatool-0.0.4.dist-info/WHEEL
wikidatatool-0.0.4.dist-info/entry_points.txt
wikidatatool-0.0.4.dist-info/top_level.txt
wikidatatool-0.0.4.dist-info/RECORD
